README.rst
setup.cfg
setup.py
./__init__.py
./i18n.py
./tryton.cfg
./user.py
./user.xml
./tests/__init__.py
./tests/test_facebook_login.py
./tests/test_view_depends.py
./view/website_form.xml
trytond_nereid_auth_facebook.egg-info/PKG-INFO
trytond_nereid_auth_facebook.egg-info/SOURCES.txt
trytond_nereid_auth_facebook.egg-info/dependency_links.txt
trytond_nereid_auth_facebook.egg-info/entry_points.txt
trytond_nereid_auth_facebook.egg-info/not-zip-safe
trytond_nereid_auth_facebook.egg-info/requires.txt
trytond_nereid_auth_facebook.egg-info/top_level.txt