Metadata-Version: 1.1
Name: trytond-nereid-auth-facebook
Version: 3.2.1.0
Summary: Nereid User Authentication using Facebook
Home-page: http://www.openlabs.co.in
Author: Openlabs Technologies and Consulting P Ltd.
Author-email: UNKNOWN
License: GPL-3
Platform: UNKNOWN
Classifier: Development Status :: 5 - Production/Stable
Classifier: Environment :: Plugins
Classifier: Framework :: Tryton
Classifier: Intended Audience :: Developers
Classifier: Intended Audience :: Financial and Insurance Industry
Classifier: Intended Audience :: Legal Industry
Classifier: Intended Audience :: Manufacturing
Classifier: License :: OSI Approved :: GNU General Public License (GPL)
Classifier: Natural Language :: English
Classifier: Operating System :: OS Independent
Classifier: Programming Language :: Python :: 2.7
Classifier: Topic :: Office/Business
